LICENSE
MANIFEST.in
readme.md
setup.py
jTransliterate/__init__.py
jTransliterate/test.py
jTransliterate/translation_maps.py
jTransliterate.egg-info/PKG-INFO
jTransliterate.egg-info/SOURCES.txt
jTransliterate.egg-info/dependency_links.txt
jTransliterate.egg-info/top_level.txt