Metadata-Version: 1.0
Name: jTransliterate
Version: 1.0.3
Summary: Transliterate [Hirag/Katak]ana to Latin/English and back. Convert half/full-width Japanese text.
Home-page: https://github.com/ryanmcgrath/jTransliterate
Author: Ryan McGrath
Author-email: ryan@venodesigns.net
License: MIT License
Keywords: japanese translation transliterate katakana hiragana latin romaji
Platform: UNKNOWN
Classifier: Development Status :: 4 - Beta
Classifier: Intended Audience :: Developers
Classifier: License :: OSI Approved :: MIT License
Classifier: Topic :: Software Development :: Libraries :: Python Modules
Classifier: Topic :: Communications :: Chat
Classifier: Topic :: Internet
